{"info": {"name": "external", "date_created": "03/08/2022"}, "images": {"id": 1, "width": 800, "height": 1067, "file_name": "0000349_as-0000088.jpg"}, "annotations": [{"id": 4, "image_id": 1, "category_id": "as-0000088", "segmentation": [[[[29, 370], [72, 381], [79, 391], [88, 417], [96, 438], [104, 447], [136, 457], [250, 472], [464, 492], [569, 498], [586, 496], [598, 488], [615, 459], [627, 431], [679, 425], [727, 416], [746, 401], [755, 430], [745, 496], [742, 552], [710, 609], [698, 626], [676, 635], [651, 638], [644, 628], [626, 620], [557, 625], [548, 636], [555, 644], [421, 636], [252, 616], [164, 595], [146, 593], [136, 590], [126, 574], [72, 556], [67, 561], [67, 564], [35, 531], [16, 489], [13, 440], [7, 402], [8, 382], [16, 361], [29, 370]]]], "area": 111695.0, "bbox": [7, 361, 748, 283], "damage": null, "part": "Rear bumper", "year": 2018, "color": "Black", "level": 4, "repair": ["Rear bumper:coating", "Rear fender(R):coating,sheet_metal", "Rear door(R):coating,sheet_metal"]}], "categories": {"id": "as-0000088", "supercategory_name": "Full-size car"}}